[
 {
   "firstName": "Kareem",
   "lastName": "Hunt",
   "Pos": "RB",
   "Team": "KCC",
   "Salary": "$8.3K",
   "GP": 2,
   "FPPG": 33.75,
   "FPMAX": 43.1,
   "Floor": 24.4,
   "Ceil": 43.1
 },
 {
   "firstName": "Todd",
   "lastName": "Gurley",
   "Pos": "RB",
   "Team": "LAR",
   "Salary": "$7.9K",
   "GP": 2,
   "FPPG": 21.6,
   "FPMAX": 25.1,
   "Floor": 18.1,
   "Ceil": 25.1
 },
 {
   "firstName": "Ty",
   "lastName": "Montgomery",
   "Pos": "RB",
   "Team": "GBP",
   "Salary": "$7.2K",
   "GP": 2,
   "FPPG": 21.65,
   "FPMAX": 26,
   "Floor": 17.3,
   "Ceil": 26
 },
 {
   "firstName": "Melvin",
   "lastName": "Gordon",
   "Pos": "RB",
   "Team": "LAC",
   "Salary": "$7.6K",
   "GP": 2,
   "FPPG": 16.85,
   "FPMAX": 17.3,
   "Floor": 16.4,
   "Ceil": 17.3
 },
 {
   "firstName": "Jay",
   "lastName": "Ajayi",
   "Pos": "RB",
   "Team": "MIA",
   "Salary": "$8.2K",
   "GP": 1,
   "FPPG": 13.6,
   "FPMAX": 13.6,
   "Floor": 13.6,
   "Ceil": 13.6
 },
 {
   "firstName": "Chris",
   "lastName": "Thompson",
   "Pos": "RB",
   "Team": "WAS",
   "Salary": "$5.6K",
   "GP": 2,
   "FPPG": 18.85,
   "FPMAX": 24.1,
   "Floor": 13.6,
   "Ceil": 24.1
 },
 {
   "firstName": "Leonard",
   "lastName": "Fournette",
   "Pos": "RB",
   "Team": "JAC",
   "Salary": "$7.4K",
   "GP": 2,
   "FPPG": 16.5,
   "FPMAX": 19.9,
   "Floor": 13.1,
   "Ceil": 19.9
 },
 {
   "firstName": "Mike",
   "lastName": "Gillislee",
   "Pos": "RB",
   "Team": "NEP",
   "Salary": "$6.8K",
   "GP": 2,
   "FPPG": 17.7,
   "FPMAX": 22.5,
   "Floor": 12.9,
   "Ceil": 22.5
 },
 {
   "firstName": "Jacquizz",
   "lastName": "Rodgers",
   "Pos": "RB",
   "Team": "TBB",
   "Salary": "$6.6K",
   "GP": 1,
   "FPPG": 12.7,
   "FPMAX": 12.7,
   "Floor": 12.7,
   "Ceil": 12.7
 },
 {
   "firstName": "Terrance",
   "lastName": "West",
   "Pos": "RB",
   "Team": "BAL",
   "Salary": "$6.7K",
   "GP": 2,
   "FPPG": 12.75,
   "FPMAX": 14,
   "Floor": 11.5,
   "Ceil": 14
 },
 {
   "firstName": "Devonta",
   "lastName": "Freeman",
   "Pos": "RB",
   "Team": "ATL",
   "Salary": "$8.2K",
   "GP": 2,
   "FPPG": 16.95,
   "FPMAX": 23,
   "Floor": 10.9,
   "Ceil": 23
 },
 {
   "firstName": "Carlos",
   "lastName": "Hyde",
   "Pos": "RB",
   "Team": "SFO",
   "Salary": "$6.6K",
   "GP": 2,
   "FPPG": 13.25,
   "FPMAX": 15.8,
   "Floor": 10.7,
   "Ceil": 15.8
 },
 {
   "firstName": "Lamar",
   "lastName": "Miller",
   "Pos": "RB",
   "Team": "HOU",
   "Salary": "$6.1K",
   "GP": 2,
   "FPPG": 10.4,
   "FPMAX": 10.6,
   "Floor": 10.2,
   "Ceil": 10.6
 },
 {
   "firstName": "David",
   "lastName": "Johnson",
   "Pos": "RB",
   "Team": "ARI",
   "Salary": "$0.00",
   "GP": 1,
   "FPPG": 10.1,
   "FPMAX": 10.1,
   "Floor": 10.1,
   "Ceil": 10.1
 },
 {
   "firstName": "Marshawn",
   "lastName": "Lynch",
   "Pos": "RB",
   "Team": "OAK",
   "Salary": "$6.7K",
   "GP": 2,
   "FPPG": 10.55,
   "FPMAX": 11.4,
   "Floor": 9.7,
   "Ceil": 11.4
 },
 {
   "firstName": "Mark",
   "lastName": "Ingram",
   "Pos": "RB",
   "Team": "NOS",
   "Salary": "$5.8K",
   "GP": 2,
   "FPPG": 9.6,
   "FPMAX": 9.6,
   "Floor": 9.6,
   "Ceil": 9.6
 },
 {
   "firstName": "C.J.",
   "lastName": "Anderson",
   "Pos": "RB",
   "Team": "DEN",
   "Salary": "$6.9K",
   "GP": 2,
   "FPPG": 19.1,
   "FPMAX": 28.9,
   "Floor": 9.3,
   "Ceil": 28.9
 },
 {
   "firstName": "Charcandrick",
   "lastName": "West",
   "Pos": "RB",
   "Team": "KCC",
   "Salary": "$5.1K",
   "GP": 1,
   "FPPG": 9,
   "FPMAX": 9,
   "Floor": 9,
   "Ceil": 9
 },
 {
   "firstName": "Tarik",
   "lastName": "Cohen",
   "Pos": "RB",
   "Team": "CHI",
   "Salary": "$5.6K",
   "GP": 2,
   "FPPG": 15.05,
   "FPMAX": 21.3,
   "Floor": 8.8,
   "Ceil": 21.3
 },
 {
   "firstName": "James",
   "lastName": "White",
   "Pos": "RB",
   "Team": "NEP",
   "Salary": "$5.6K",
   "GP": 2,
   "FPPG": 10.95,
   "FPMAX": 13.6,
   "Floor": 8.3,
   "Ceil": 13.6
 },
 {
   "firstName": "Tevin",
   "lastName": "Coleman",
   "Pos": "RB",
   "Team": "ATL",
   "Salary": "$5.5K",
   "GP": 2,
   "FPPG": 9.65,
   "FPMAX": 11.5,
   "Floor": 7.8,
   "Ceil": 11.5
 },
 {
   "firstName": "Dalvin",
   "lastName": "Cook",
   "Pos": "RB",
   "Team": "MIN",
   "Salary": "$6.5K",
   "GP": 2,
   "FPPG": 11.3,
   "FPMAX": 15.2,
   "Floor": 7.4,
   "Ceil": 15.2
 },
 {
   "firstName": "LeSean",
   "lastName": "McCoy",
   "Pos": "RB",
   "Team": "BUF",
   "Salary": "$8.1K",
   "GP": 2,
   "FPPG": 12.85,
   "FPMAX": 18.4,
   "Floor": 7.3,
   "Ceil": 18.4
 },
 {
   "firstName": "Samaje",
   "lastName": "Perine",
   "Pos": "RB",
   "Team": "WAS",
   "Salary": "$5.6K",
   "GP": 1,
   "FPPG": 7.2,
   "FPMAX": 7.2,
   "Floor": 7.2,
   "Ceil": 7.2
 },
 {
   "firstName": "Javorius",
   "lastName": "Allen",
   "Pos": "RB",
   "Team": "BAL",
   "Salary": "$5.7K",
   "GP": 2,
   "FPPG": 12.85,
   "FPMAX": 18.6,
   "Floor": 7.1,
   "Ceil": 18.6
 },
 {
   "firstName": "Shane",
   "lastName": "Vereen",
   "Pos": "RB",
   "Team": "NYG",
   "Salary": "$4.8K",
   "GP": 2,
   "FPPG": 8.3,
   "FPMAX": 9.6,
   "Floor": 7,
   "Ceil": 9.6
 },
 {
   "firstName": "Darren",
   "lastName": "Sproles",
   "Pos": "RB",
   "Team": "PHI",
   "Salary": "$5.2K",
   "GP": 2,
   "FPPG": 6.9,
   "FPMAX": 7,
   "Floor": 6.8,
   "Ceil": 7
 },
 {
   "firstName": "Tommy",
   "lastName": "Bohanon",
   "Pos": "RB",
   "Team": "JAC",
   "Salary": "$4.5K",
   "GP": 1,
   "FPPG": 6.6,
   "FPMAX": 6.6,
   "Floor": 6.6,
   "Ceil": 6.6
 },
 {
   "firstName": "Christian",
   "lastName": "McCaffrey",
   "Pos": "RB",
   "Team": "CAR",
   "Salary": "$6.8K",
   "GP": 2,
   "FPPG": 7.7,
   "FPMAX": 9,
   "Floor": 6.4,
   "Ceil": 9
 },
 {
   "firstName": "Jalston",
   "lastName": "Fowler",
   "Pos": "RB",
   "Team": "TEN",
   "Salary": "$4.5K",
   "GP": 1,
   "FPPG": 6.3,
   "FPMAX": 6.3,
   "Floor": 6.3,
   "Ceil": 6.3
 },
 {
   "firstName": "Le'Veon",
   "lastName": "Bell",
   "Pos": "RB",
   "Team": "PIT",
   "Salary": "$8.7K",
   "GP": 2,
   "FPPG": 8.65,
   "FPMAX": 11.1,
   "Floor": 6.2,
   "Ceil": 11.1
 },
 {
   "firstName": "CJ",
   "lastName": "Ham",
   "Pos": "RB",
   "Team": "MIN",
   "Salary": "$0.00",
   "GP": 1,
   "FPPG": 6.1,
   "FPMAX": 6.1,
   "Floor": 6.1,
   "Ceil": 6.1
 },
 {
   "firstName": "Chris",
   "lastName": "Ivory",
   "Pos": "RB",
   "Team": "JAC",
   "Salary": "$4.7K",
   "GP": 2,
   "FPPG": 6.05,
   "FPMAX": 6.3,
   "Floor": 5.8,
   "Ceil": 6.3
 },
 {
   "firstName": "Alvin",
   "lastName": "Kamara",
   "Pos": "RB",
   "Team": "NOS",
   "Salary": "$5.2K",
   "GP": 2,
   "FPPG": 6.35,
   "FPMAX": 6.9,
   "Floor": 5.8,
   "Ceil": 6.9
 },
 {
   "firstName": "Frank",
   "lastName": "Gore",
   "Pos": "RB",
   "Team": "IND",
   "Salary": "$6.3K",
   "GP": 2,
   "FPPG": 8.15,
   "FPMAX": 10.6,
   "Floor": 5.7,
   "Ceil": 10.6
 }
]
